setup.py
bank_transactions/__init__.py
bank_transactions/parser.py
bank_transactions/parser_old.py
bank_transactions.egg-info/PKG-INFO
bank_transactions.egg-info/SOURCES.txt
bank_transactions.egg-info/dependency_links.txt
bank_transactions.egg-info/not-zip-safe
bank_transactions.egg-info/requires.txt
bank_transactions.egg-info/top_level.txt