Metadata-Version: 1.0
Name: bank-transactions
Version: 0.3
Summary: Python package for importing bank transaction files.
Home-page: https://github.com/henkvanramshorst/bank_transactions
Author: Henk van Ramshorst
Author-email: henk@vanramshorst.nl
License: MIT
Platform: UNKNOWN
